satnogs_db_api_client-1.72.dist-info/licenses/LICENSE
satnogsdbapiclient/__init__.py
satnogsdbapiclient/_version.py
satnogsdbapiclient/api_client.py
satnogsdbapiclient/api_response.py
satnogsdbapiclient/configuration.py
satnogsdbapiclient/exceptions.py
satnogsdbapiclient/rest.py
satnogsdbapiclient/api/__init__.py
satnogsdbapiclient/api/artifacts_api.py
satnogsdbapiclient/api/decoded_frame_api.py
satnogsdbapiclient/api/modes_api.py
satnogsdbapiclient/api/optical_observations_api.py
satnogsdbapiclient/api/satellites_api.py
satnogsdbapiclient/api/telemetry_api.py
satnogsdbapiclient/api/tle_api.py
satnogsdbapiclient/api/transmitters_api.py
satnogsdbapiclient/models/__init__.py
satnogsdbapiclient/models/artifact.py
satnogsdbapiclient/models/iaru_coordination_enum.py
satnogsdbapiclient/models/inline_decoded_frame_request.py
satnogsdbapiclient/models/latest_tle_set.py
satnogsdbapiclient/models/mode.py
satnogsdbapiclient/models/new_artifact.py
satnogsdbapiclient/models/optical_identification.py
satnogsdbapiclient/models/optical_observation.py
satnogsdbapiclient/models/optical_observation_create.py
satnogsdbapiclient/models/paginated_artifact_list.py
satnogsdbapiclient/models/paginated_telemetry_list.py
satnogsdbapiclient/models/satellite.py
satnogsdbapiclient/models/service_enum.py
satnogsdbapiclient/models/status_enum.py
satnogsdbapiclient/models/telemetry.py
satnogsdbapiclient/models/telemetry_request.py
satnogsdbapiclient/models/transmitter.py
satnogsdbapiclient/models/transmitter_request.py
satnogsdbapiclient/models/type_enum.py
satnogsdbapiclient/test/__init__.py
satnogsdbapiclient/test/test_artifact.py
satnogsdbapiclient/test/test_artifacts_api.py
satnogsdbapiclient/test/test_decoded_frame_api.py
satnogsdbapiclient/test/test_iaru_coordination_enum.py
satnogsdbapiclient/test/test_inline_decoded_frame_request.py
satnogsdbapiclient/test/test_latest_tle_set.py
satnogsdbapiclient/test/test_mode.py
satnogsdbapiclient/test/test_modes_api.py
satnogsdbapiclient/test/test_new_artifact.py
satnogs_db_api_client-1.72.dist-info/METADATA
satnogs_db_api_client-1.72.dist-info/WHEEL
satnogs_db_api_client-1.72.dist-info/top_level.txt
satnogs_db_api_client-1.72.dist-info/RECORD
