Metadata-Version: 2.4
Name: satnogs-db-api-client
Version: 1.72
Summary: SatNOGS DB API Client
Home-page: https://gitlab.com/librespacefoundation/satnogs/satnogs-db
Author: SatNOGS project
Author-email: dev@satnogs.org
License: AGPLv3
Classifier: Development Status :: 4 - Beta
Classifier: Environment :: Web Environment
Classifier: Framework :: Django
Classifier: Intended Audience :: Telecommunications Industry
Classifier: Intended Audience :: Science/Research
Classifier: License :: OSI Approved :: GNU Affero General Public License v3
Classifier: Operating System :: POSIX :: Linux
Classifier: Programming Language :: Python
Classifier: Programming Language :: Python :: 3
Classifier: Topic :: Communications :: Ham Radio
Classifier: Topic :: Internet :: WWW/HTTP
Classifier: Topic :: Internet :: WWW/HTTP :: Dynamic Content
License-File: LICENSE
Requires-Dist: urllib3~=2.5.0
Requires-Dist: python-dateutil~=2.9.0
Requires-Dist: pydantic~=2.11.0
Requires-Dist: typing-extensions~=4.14.0
Requires-Dist: versioneer~=0.29.0
Provides-Extra: dev
Requires-Dist: build~=1.2.0; extra == "dev"
Requires-Dist: tox~=4.27.0; extra == "dev"
Requires-Dist: twine~=6.1.0; extra == "dev"
Dynamic: license-file
